{"bookId":"23152F34-5D63-4213-84BD-0CFF085E943A","content":"##思考\n    首先，我们确定真正的杀人凶手就是科学怪人。\n    科学怪人的杀人手法我们需要去考虑。\n    首先，第一点，整个故事中，想要杀死鬼王的有三个人。\n    第一个人是木乃伊，他的杀人手法是将拉迪斯之泪滴入鬼王的酒杯中。\n    第二个人是女巫，他的杀人手法同样还是使用xx之粉，他的做法是来到厨房将所有的杯子中都滴入xx之粉。（所以说这里要设置一个线索）\n    第三个人就是狼王，他的杀人手法是补刀。他不确定木乃伊是否会将拉迪斯之泪放入鬼王的酒杯中，所以他需要做的就是补刀。如果鬼王没有死，他需要进去杀死他，如果鬼王死了，他就不需要行动了。\n    \n    现在的问题是木乃伊的杀人手法过于简单，如果想要设置线索的话，就只能是被别人看到，这样做的后果就是木乃伊可能直接背锅被投死。所以，我现在要死思考的是，强化木乃伊的杀人手法，增加一点诡计进去。\n    或者说，我们可以设置误杀的桥段。本来是，女巫来杀科学怪人的，但是不小心杀了鬼王。之类的吧。至于谁误杀谁，我们需要考虑一下。\n    第一，科学怪人是要杀死鬼王的，这个不能改变。而且他也需要看到女巫和狼王，鬼王之间的内讧。\n    所以蒂夫给狼王制作了毒药，交给他的条件就是需要带上她来到城堡中，见上迪娜一眼。","creationTime":652282057.09717202,"id":"46E335CC-95DD-4235-8B67-7898CE98799B","lastEditTime":652279932.54115796,"title":"思考","words":543,"manuscriptId":"39DF0B01-1D56-4A2B-8924-4709B8B879F3"}